aea_ledger_ethereum_flashbots/__init__.py
aea_ledger_ethereum_flashbots/ethereum_flashbots.py
aea_ledger_ethereum_flashbots/py.typed
open_aea_ledger_ethereum_flashbots-2.0.8.dist-info/licenses/LICENSE
open_aea_ledger_ethereum_flashbots-2.0.8.dist-info/METADATA
open_aea_ledger_ethereum_flashbots-2.0.8.dist-info/WHEEL
open_aea_ledger_ethereum_flashbots-2.0.8.dist-info/entry_points.txt
open_aea_ledger_ethereum_flashbots-2.0.8.dist-info/top_level.txt
open_aea_ledger_ethereum_flashbots-2.0.8.dist-info/RECORD
