Metadata-Version: 2.4
Name: open-aea-ledger-ethereum-flashbots
Version: 2.0.8
Summary: Python package extending the default open-aea ethereum ledger plugin to add support for flashbots.
Author: Valory AG
License: Apache-2.0
Classifier: Environment :: Console
Classifier: Environment :: Web Environment
Classifier: Development Status :: 5 - Production/Stable
Classifier: Intended Audience :: Developers
Classifier: License :: OSI Approved :: Apache Software License
Classifier: Natural Language :: English
Classifier: Operating System :: MacOS
Classifier: Operating System :: Microsoft
Classifier: Operating System :: Unix
Classifier: Programming Language :: Python :: 3.10
Classifier: Programming Language :: Python :: 3.11
Classifier: Topic :: Communications
Classifier: Topic :: Internet
Classifier: Topic :: Software Development
Requires-Python: >=3.10,<4.0
License-File: LICENSE
Requires-Dist: open-aea-ledger-ethereum~=2.0.0
Requires-Dist: open-aea-flashbots==2.0.0
Dynamic: author
Dynamic: classifier
Dynamic: description
Dynamic: description-content-type
Dynamic: license
Dynamic: license-file
Dynamic: requires-dist
Dynamic: requires-python
Dynamic: summary
